{
  "version": "founder",
  "outputFile": "Shivam_Bhardwaj_Resume_Founder",
  "tagline": "Founder & Robotics Architect | Building AI-Native Hardware Systems",
  "showVisaBadge": false,
  "visaBadgeText": "",
  "summary": "<strong>Visionary Engineer & Founder</strong> with 6+ years architecting zero-to-one automation for <strong>Meta, Applied Materials, and Saildrone</strong>. Specialist in collapsing development cycles (100x speedups) via custom <strong>AI-driven CAD & Manufacturing engines</strong>. Now building the next generation of <strong>autonomous industrial robotics</strong>.",
  "sections": {
    "summary": true,
    "skills": true,
    "experience": true,
    "education": true
  },
  "experienceOrder": [
    "design-visionaries",
    "aes",
    "velodyne",
    "monogram"
  ],
  "skillsOrder": [
    "AI & Robotics",
    "Hardware/CAD",
    "Automation",
    "Process/Tools"
  ],
  "experienceOverrides": {
    "design-visionaries": {
      "title": "Founder & Lead Engineer",
      "subtitle": "Consulting for Applied Materials, Saildrone, Industrial Clients"
    },
    "aes": {
      "title": "Engineering Lead",
      "subtitle": "Led cross-functional teams for Meta & Applied Materials"
    }
  }
}